fullAdderusingHA/fullAdder.v
module halfAdder(
    input a,
    input b,
    output sum,
    output carry
);
    assign sum = a ^ b;      // Sum is the XOR of a and b
    assign carry = a & b;    // Carry is the AND of a and b
endmodule

module fullAdder(
    input a,
    input b,
    input c_in,
    output sum,
    output c_out
);
    wire sum_half1, carry_half1, carry_half2;

    // First half adder
    halfAdder HA1 (
        .a(a),
        .b(b),
        .sum(sum_half1),
        .carry(carry_half1)
    );

    // Second half adder
    halfAdder HA2 (
        .a(sum_half1),
        .b(c_in),
        .sum(sum),
        .carry(carry_half2)
    );

    // Final carry out
    assign c_out = carry_half1 | carry_half2;
endmodule

fullAdderusingHA/fullAdder_tb.v
module fullAdder_tb;
  reg a,b,c_in;
  wire sum,c_out;

  fullAdder U1 (a,b,c_in,sum,c_out);

  initial begin
    $dumpfile("fullAdder_tb.vcd");
    $dumpvars(0, fullAdder_tb);
    $monitor($time," a=%b b=%b c_in=%b | sum=%b c_out=%b",
              a, b, c_in, sum, c_out);
    a = 0; b = 0; c_in = 0;
    #10 a = 0; b = 0; c_in = 1;
    #10 a = 0; b = 1; c_in = 0;
    #10 a = 0; b = 1; c_in = 1;
    #10 a = 1; b = 0; c_in = 0;
    #10 a = 1; b = 0; c_in = 1;
    #10 a = 1; b = 1; c_in = 0;
    #10 a = 1; b = 1; c_in = 1;
    #10 $finish;
  end
endmodule

fullAdderusingHA/fullAdder_tb.vcd
$date
	Fri Jan 23 14:51:43 2026
$end
$version
	Icarus Verilog
$end
$timescale
	1s
$end
$scope module fullAdder_tb $end
$var wire 1 ! sum $end
$var wire 1 " c_out $end
$var reg 1 # a $end
$var reg 1 $ b $end
$var reg 1 % c_in $end
$scope module U1 $end
$var wire 1 # a $end
$var wire 1 $ b $end
$var wire 1 % c_in $end
$var wire 1 " c_out $end
$var wire 1 & sum_half1 $end
$var wire 1 ! sum $end
$var wire 1 ' carry_half2 $end
$var wire 1 ( carry_half1 $end
$scope module HA1 $end
$var wire 1 # a $end
$var wire 1 $ b $end
$var wire 1 ( carry $end
$var wire 1 & sum $end
$upscope $end
$scope module HA2 $end
$var wire 1 & a $end
$var wire 1 % b $end
$var wire 1 ' carry $end
$var wire 1 ! sum $end
$upscope $end
$upscope $end
$upscope $end
$enddefinitions $end
$comment Show the parameter values. $end
$dumpall
$end
#0
$dumpvars
0(
0'
0&
0%
0$
0#
0"
0!
$end
#10
1!
1%
#20
1&
0%
1$
#30
1"
0!
1'
1%
#40
0"
1!
0'
0%
0$
1#
#50
1"
0!
1'
1%
#60
0'
0&
1(
0%
1$
#70
1!
1%
