qn6/primeDetector.v
module primeDetector(M,Y);
input [3:0] M;
output Y;
wire a,b,c,d;

and g1(a,~M[3],M[0]);
and g2(b,~M[3],~M[2],M[1]);
and g3(c,M[2],~M[1],M[0]);
and g4(d,~M[2],M[1],M[0]);
or g5(Y,a,b,c,d);
endmodule

primeNumberDetector/prime_tb.v
module prime_tb;
reg[3:0] M;
wire Y;

primeDetector DUT(M,Y);

initial
begin
  $dumpfile("prime.vcd");
  $dumpvars(0,prime_tb);
  $monitor($time," Given Number = %b | Number is Prime or Not : %b",M,Y);
  M = 4'd0;
  #10 M = 4'd1;
  #10 M = 4'd2;
  #10 M = 4'd3;
  #10 M = 4'd4;
  #10 M = 4'd5;
  #10 M = 4'd6;
  #10 M = 4'd7;
  #10 M = 4'd8;
  #10 M = 4'd9;
  #10 M = 4'd10;
  #10 M = 4'd11;
  #10 M = 4'd12;
  #10 M = 4'd13;
  #10 M = 4'd14;
  #10 M = 4'd15;
  #10 $finish;
end
endmodule

primeNumberDetector/prime.vcd
$date
	Fri Jan 23 15:10:34 2026
$end
$version
	Icarus Verilog
$end
$timescale
	1s
$end
$scope module prime_tb $end
$var wire 1 ! Y $end
$var reg 4 " M [3:0] $end
$scope module DUT $end
$var wire 4 # M [3:0] $end
$var wire 1 ! Y $end
$var wire 1 $ a $end
$var wire 1 % b $end
$var wire 1 & c $end
$var wire 1 ' d $end
$upscope $end
$upscope $end
$enddefinitions $end
$comment Show the parameter values. $end
$dumpall
$end
#0
$dumpvars
0'
0&
0%
0$
b0 #
b0 "
0!
$end
#10
1!
1$
b1 "
b1 #
#20
0$
1%
b10 "
b10 #
#30
1$
1'
b11 "
b11 #
#40
0!
0$
0%
0'
b100 "
b100 #
#50
1!
1$
1&
b101 "
b101 #
#60
0!
0$
0&
b110 "
b110 #
#70
1!
1$
b111 "
b111 #
#80
0!
0$
b1000 "
b1000 #
#90
b1001 "
b1001 #
#100
b1010 "
b1010 #
#110
1!
1'
b1011 "
b1011 #
#120
0!
0'
b1100 "
b1100 #
#130
1!
1&
b1101 "
b1101 #
#140
0!
0&
b1110 "
b1110 #
#150
b1111 "
b1111 #
