fullSubtractor/fullSubtractor.v
module halfSubtractor(a,b,diff,borrow);
input a,b;
output diff,borrow;

assign diff = a ^ b;
assign borrow = ~a & b;

endmodule

module fullSubtractor(a,b,c,diff,borrow);

input a,b,c;
output diff,borrow;
wire w1,w2,w3;
halfSubtractor H1(a,b,w1,w2);
halfSubtractor H2(w1,c,diff,w3);
or O1(borrow,w2,w3);

endmodule

fullSubtractor/fullSubtractor_tb.v
module fullSubtractor_tb;
reg a,b,c;
wire diff,borrow;

fullSubtractor DUT(a,b,c,diff,borrow);

initial
begin
  $dumpfile("subtractor.vcd");
  $dumpvars(0,fullSubtractor_tb);
  $monitor($time," a = %b , b = %b , c = %b | diff = %b | borrow = %b",a,b,c,diff,borrow);
  a = 0; b = 0; c = 0;
  #10 a = 0; b = 0; c = 1;
  #10 a = 0; b = 1; c = 0;
  #10 a = 0; b = 1; c = 1;
  #10 a = 1; b = 0; c = 0;
  #10 a = 1; b = 0; c = 1;
  #10 a = 1; b = 1; c = 0;
  #10 a = 1; b = 1; c = 1;
  #10 $finish;
end
endmodule

fullSubtractor/subtractor.vcd
$date
	Fri Jan 23 15:48:57 2026
$end
$version
	Icarus Verilog
$end
$timescale
	1s
$end
$scope module fullSubtractor_tb $end
$var wire 1 ! diff $end
$var wire 1 " borrow $end
$var reg 1 # a $end
$var reg 1 $ b $end
$var reg 1 % c $end
$scope module DUT $end
$var wire 1 # a $end
$var wire 1 $ b $end
$var wire 1 " borrow $end
$var wire 1 % c $end
$var wire 1 & w3 $end
$var wire 1 ' w2 $end
$var wire 1 ( w1 $end
$var wire 1 ! diff $end
$scope module H1 $end
$var wire 1 # a $end
$var wire 1 $ b $end
$var wire 1 ' borrow $end
$var wire 1 ( diff $end
$upscope $end
$scope module H2 $end
$var wire 1 ( a $end
$var wire 1 % b $end
$var wire 1 & borrow $end
$var wire 1 ! diff $end
$upscope $end
$upscope $end
$upscope $end
$enddefinitions $end
$comment Show the parameter values. $end
$dumpall
$end
#0
$dumpvars
0(
0'
0&
0%
0$
0#
0"
0!
$end
#10
1"
1!
1&
1%
#20
0&
1(
1'
0%
1$
#30
0!
1%
#40
0"
1!
0'
0%
0$
1#
#50
0!
1%
#60
0(
0%
1$
#70
1"
1!
1&
1%
