fullAdder/fullAdder.v
module fullAdder_dflow(a,b,c_in,sum_d,c_out_d);
  input a,b,c_in;
  output sum_d,c_out_d;

  assign {c_out_d,sum_d} = a + b + c_in;

endmodule

module fullAdder_behav(a,b,c_in,sum_b,c_out_b);
  input a,b,c_in;
  output reg sum_b,c_out_b;

  always @(a or b or c_in) begin
    {c_out_b,sum_b} = a + b + c_in;
  end
endmodule

module fullAdder_struct(a,b,c_in,sum_s,c_out_s);
  input a,b,c_in;
  output sum_s,c_out_s;

  wire s1,c1,c2;

  xor U1 (s1, a, b);
  xor U2 (sum_s, s1, c_in);
  and U3 (c1, a, b);
  and U4 (c2, s1, c_in);
  or  U5 (c_out_s, c1, c2);
endmodule

fullAdder/fa_tb.v
module fullAdder_tb;
  reg a,b,c_in;
  wire sum_d,c_out_d;
  wire sum_b,c_out_b;
  wire sum_s,c_out_s;

  fullAdder_dflow U1 (a,b,c_in,sum_d,c_out_d);
  fullAdder_behav U2 (a,b,c_in,sum_b,c_out_b);
  fullAdder_struct U3 (a,b,c_in,sum_s,c_out_s);

  initial begin
    $dumpfile("fullAdder_tb.vcd");
    $dumpvars(0, fullAdder_tb);
    $monitor("time = %0t | a=%b b=%b c_in=%b | dflow: sum=%b c_out=%b | behav: sum=%b c_out=%b | struct: sum=%b c_out=%b",$time,
              a, b, c_in, sum_d, c_out_d, sum_b, c_out_b, sum_s, c_out_s);
    a = 0; b = 0; c_in = 0;
    #10 a = 0; b = 0; c_in = 1;
    #10 a = 0; b = 1; c_in = 0;
    #10 a = 0; b = 1; c_in = 1;
    #10 a = 1; b = 0; c_in = 0;
    #10 a = 1; b = 0; c_in = 1;
    #10 a = 1; b = 1; c_in = 0;
    #10 a = 1; b = 1; c_in = 1;
    #10 $finish;
  end
endmodule

fullAdder/fullAdder_tb.vcd
$date
	Fri Jan 23 14:39:20 2026
$end
$version
	Icarus Verilog
$end
$timescale
	1s
$end
$scope module fullAdder_tb $end
$var wire 1 ! sum_s $end
$var wire 1 " sum_d $end
$var wire 1 # sum_b $end
$var wire 1 $ c_out_s $end
$var wire 1 % c_out_d $end
$var wire 1 & c_out_b $end
$var reg 1 ' a $end
$var reg 1 ( b $end
$var reg 1 ) c_in $end
$scope module U1 $end
$var wire 1 ' a $end
$var wire 1 ( b $end
$var wire 1 ) c_in $end
$var wire 1 " sum_d $end
$var wire 1 % c_out_d $end
$upscope $end
$scope module U2 $end
$var wire 1 ' a $end
$var wire 1 ( b $end
$var wire 1 ) c_in $end
$var reg 1 & c_out_b $end
$var reg 1 # sum_b $end
$upscope $end
$scope module U3 $end
$var wire 1 ' a $end
$var wire 1 ( b $end
$var wire 1 * c1 $end
$var wire 1 + c2 $end
$var wire 1 ) c_in $end
$var wire 1 $ c_out_s $end
$var wire 1 , s1 $end
$var wire 1 ! sum_s $end
$upscope $end
$upscope $end
$enddefinitions $end
$comment Show the parameter values. $end
$dumpall
$end
#0
$dumpvars
0,
0+
0*
0)
0(
0'
0&
0%
0$
0#
0"
0!
$end
#10
1"
1#
1!
1)
#20
1,
0)
1(
#30
1$
0"
1%
1&
0#
0!
1+
1)
#40
0$
0%
1!
0+
1"
0&
1#
0)
0(
1'
#50
1$
0"
1%
1&
0#
0!
1+
1)
#60
0+
0,
1*
0)
1(
#70
1"
1#
1!
1)
