decoder3x8/decoder3_8.v
module decoder3_8(I,en,Y);
input[2:0] I;
input en;
output[7:0] Y;

// decoder logic without using enable pin
// and a1(Y[0],~I[2],~I[1],~I[0]);
// and a2(Y[1],~I[2],~I[1],I[0]);
// and a3(Y[2],~I[2],I[1],~I[0]);
// and a4(Y[3],~I[2],I[1],I[0]);
// and a5(Y[4],I[2],~I[1],~I[0]);
// and a6(Y[5],I[2],~I[1],I[0]);
// and a7(Y[6],I[2],I[1],~I[0]);
// and a8(Y[7],I[2],I[1],I[0]);

// decoder logic  using enable pin
and a1(Y[0],~I[2],~I[1],~I[0],en);
and a2(Y[1],~I[2],~I[1],I[0],en);
and a3(Y[2],~I[2],I[1],~I[0],en);
and a4(Y[3],~I[2],I[1],I[0],en);
and a5(Y[4],I[2],~I[1],~I[0],en);
and a6(Y[5],I[2],~I[1],I[0],en);
and a7(Y[6],I[2],I[1],~I[0],en);
and a8(Y[7],I[2],I[1],I[0],en);

endmodule

decoder3x8/decoder_tb.v
module decoder_tb;
reg[2:0] I; 
reg en;
wire[7:0] Y;

decoder3_8 DUT(I,en,Y);

initial
begin
  $dumpfile("decoder.vcd");
  $dumpvars(0,decoder_tb);
  $monitor($time," Input = %b Enable = %b | Output = %b",I,en,Y);
  I = 3'd7; en=0;
  #10 I = 3'd7; en=1;
  #10 I=3'd6;
  #10 I=3'd5;
  #10 I=3'd4;
  #10 I=3'd3;
  #10 en=0;
  #10 I=3'd2; en=1;
  #10 I=3'd1;
  #10 I=3'd0;
  #10 $finish;
end
endmodule

decoder3x8/decoder.vcd
$date
	Fri Jan 23 15:26:11 2026
$end
$version
	Icarus Verilog
$end
$timescale
	1s
$end
$scope module decoder_tb $end
$var wire 8 ! Y [7:0] $end
$var reg 3 " I [2:0] $end
$var reg 1 # en $end
$scope module DUT $end
$var wire 3 $ I [2:0] $end
$var wire 1 # en $end
$var wire 8 % Y [7:0] $end
$upscope $end
$upscope $end
$enddefinitions $end
$comment Show the parameter values. $end
$dumpall
$end
#0
$dumpvars
b0 %
b111 $
0#
b111 "
b0 !
$end
#10
b10000000 !
b10000000 %
1#
#20
b1000000 !
b1000000 %
b110 "
b110 $
#30
b100000 !
b100000 %
b101 "
b101 $
#40
b10000 !
b10000 %
b100 "
b100 $
#50
b1000 !
b1000 %
b11 "
b11 $
#60
b0 !
b0 %
0#
#70
b100 !
b100 %
1#
b10 "
b10 $
#80
b10 !
b10 %
b1 "
b1 $
#90
b1 !
b1 %
b0 "
b0 $
