cyclicLights/cyclicLight.v
module cyclicLight(clk,light);
input clk;
output reg [2:0] light;

parameter S0 = 2'b00;
parameter S1 = 2'b01;
parameter S2 = 2'b10;

parameter RED = 3'b100;
parameter YELLOW = 3'b010;
parameter GREEN = 3'b001;

reg [1:0] state;

always @(posedge clk)
begin
  case (state)
  S0 : begin
    light <= YELLOW;
    state <= S1;
  end
  S1 : begin
    light <= GREEN;
    state <= S2;
  end
  S2 : begin
    light <= RED;
    state <= S0;
  end
  default : begin
    light <= RED;
    state <= S0;
  end
  endcase
end
endmodule

cyclicLights/cyclicLighttb.v
module cyclicLighttb;
reg clk;
wire [2:0] light;

cyclicLight DUT(clk,light);

always #5 clk = ~clk;

initial
begin
  $dumpfile("wave.vcd");
  $dumpvars(0,cyclicLighttb);
  $monitor("Time = %t | clk = %b | light = %b",$time,clk,light);
  clk = 1'b0;
  #155 $finish;
end
endmodule

cyclicLights/wave.vcd
$date
	Sun Feb 08 23:24:12 2026
$end
$version
	Icarus Verilog
$end
$timescale
	1s
$end
$scope module cyclicLighttb $end
$var wire 3 ! light [2:0] $end
$var reg 1 " clk $end
$scope module DUT $end
$var wire 1 " clk $end
$var parameter 3 # GREEN $end
$var parameter 3 $ RED $end
$var parameter 2 % S0 $end
$var parameter 2 & S1 $end
$var parameter 2 ' S2 $end
$var parameter 3 ( YELLOW $end
$var reg 3 ) light [2:0] $end
$var reg 2 * state [1:0] $end
$upscope $end
$upscope $end
$enddefinitions $end
$comment Show the parameter values. $end
$dumpall
b10 (
b10 '
b1 &
b0 %
b100 $
b1 #
$end
#0
$dumpvars
bx *
bx )
0"
bx !
$end
#5
b0 *
b100 !
b100 )
1"
#10
0"
#15
b1 *
b10 !
b10 )
1"
#20
0"
#25
b10 *
b1 !
b1 )
1"
#30
0"
#35
b0 *
b100 !
b100 )
1"
#40
0"
#45
b1 *
b10 !
b10 )
1"
#50
0"
#55
b10 *
b1 !
b1 )
1"
#60
0"
#65
b0 *
b100 !
b100 )
1"
#70
0"
#75
b1 *
b10 !
b10 )
1"
#80
0"
#85
b10 *
b1 !
b1 )
1"
#90
0"
#95
b0 *
b100 !
b100 )
1"
#100
0"
#105
b1 *
b10 !
b10 )
1"
#110
0"
#115
b10 *
b1 !
b1 )
1"
#120
0"
#125
b0 *
b100 !
b100 )
1"
#130
0"
#135
b1 *
b10 !
b10 )
1"
#140
0"
#145
b10 *
b1 !
b1 )
1"
#150
0"
#155
b0 *
b100 !
b100 )
1"
